mcpt/__init__.py
mcpt/ci/__init__.py
mcpt/correlation_permutation_test/__init__.py
mcpt/permutation_test/__init__.py
mcpt/plot/__init__.py
mcpt-0.1.8.dist-info/LICENSE
mcpt-0.1.8.dist-info/METADATA
mcpt-0.1.8.dist-info/WHEEL
mcpt-0.1.8.dist-info/top_level.txt
mcpt-0.1.8.dist-info/RECORD
