Metadata-Version: 2.1
Name: mcpt
Version: 0.1.8
Summary: A Python library for calculating p-values using Monte Carlo sampling
Home-page: https://github.com/ravenlocke/mcpt
Author: David J. Skelton
Author-email: d.j.skelton1@gmail.com
License: MIT
Platform: UNKNOWN
Classifier: Development Status :: 5 - Production/Stable
Classifier: License :: OSI Approved :: MIT License
Classifier: Programming Language :: Python :: 3
Classifier: Programming Language :: Python :: 3.5
Classifier: Programming Language :: Python :: 3.6
Classifier: Programming Language :: Python :: 3.7
Requires-Python: ~=3.5
Requires-Dist: scipy
Requires-Dist: numpy
Requires-Dist: matplotlib
